memoframe/__init__.py
memoframe/memoframe.py
memoframe-0.1.4.dist-info/LICENSE
memoframe-0.1.4.dist-info/METADATA
memoframe-0.1.4.dist-info/WHEEL
memoframe-0.1.4.dist-info/RECORD
