Metadata-Version: 2.1
Name: memoframe
Version: 0.1.4
Summary: Python project that creates a package that optimize pandas dataframe
Author: Ilyes Braham
Requires-Python: >=3.10,<4.0
Classifier: Programming Language :: Python :: 3
Classifier: Programming Language :: Python :: 3.10
Classifier: Programming Language :: Python :: 3.11
Requires-Dist: pandas (>=1.5.2,<2.0.0)
